{"version":1,"resource":"file:///home/aaryan/projects/anmol-website/events/templates/eventCreate.html","entries":[{"id":"dupl.html","timestamp":1658082547574},{"id":"mRLK.html","timestamp":1658082561768},{"id":"b4Hu.html","timestamp":1658082917634},{"id":"nNgX.html","timestamp":1658082948861},{"id":"XwOL.html","timestamp":1658083020571},{"id":"OyLY.html","timestamp":1658083861264},{"id":"uFDc.html","timestamp":1658086673462},{"id":"xmtV.html","source":"undoRedo.source","timestamp":1658086675166}]}